peachproxy.py
peachweb_api-1.2.37.dist-info/DESCRIPTION.rst
peachweb_api-1.2.37.dist-info/METADATA
peachweb_api-1.2.37.dist-info/RECORD
peachweb_api-1.2.37.dist-info/WHEEL
peachweb_api-1.2.37.dist-info/metadata.json
peachweb_api-1.2.37.dist-info/top_level.txt
